[
    {
      "title": "Engineering Augmentation",
      "description": "Scale your team with our experienced engineers who seamlessly integrate with your workflow.",
      "icon": ""
    },
    {
      "title": "Consulting & Advisory",
      "description": "Leverage our expertise to overcome technical challenges and optimize your processes.",
      "icon": ""
    },
    {
      "title": "Product Development",
      "description": "From concept to launch, we build products that meet your business goals.",
      "icon": ""
    }
  ]
  